tagtomarkdown.py
tagtomarkdown-0.4.0.data/data/sample/Page1.html
tagtomarkdown-0.4.0.data/data/sample/Page1.md
tagtomarkdown-0.4.0.data/data/sample/README.txt
tagtomarkdown-0.4.0.data/data/sample/book.json
tagtomarkdown-0.4.0.data/data/sample/extra.css
tagtomarkdown-0.4.0.data/data/sample/mkdocs.yml
tagtomarkdown-0.4.0.data/data/sample/produceHtml.py
tagtomarkdown-0.4.0.dist-info/LICENSE.txt
tagtomarkdown-0.4.0.dist-info/METADATA
tagtomarkdown-0.4.0.dist-info/WHEEL
tagtomarkdown-0.4.0.dist-info/entry_points.txt
tagtomarkdown-0.4.0.dist-info/top_level.txt
tagtomarkdown-0.4.0.dist-info/RECORD
