Metadata-Version: 2.1
Name: tagtomarkdown
Version: 0.4.0
Summary: Python3 markdown extension for converting tags to Markdown table
Home-page: https://github.com/chrhauris/tagtomarkdown
Author: Christian Hauris Sorensen
Author-email: chrhauris@hotmail.com
License: The MIT License (MIT)
Requires-Dist: markdown
